.coveragerc
AUTHORS.rst
CHANGELOG.rst
CODE_OF_CONDUCT.rst
LICENSE
MANIFEST.in
README.rst
conftest.py
pyproject.toml
setup.cfg
setup.py
tox.ini
changelog.d/towncrier_template.rst
src/pikara/__init__.py
src/pikara/analysis.py
src/pikara.egg-info/PKG-INFO
src/pikara.egg-info/SOURCES.txt
src/pikara.egg-info/dependency_links.txt
src/pikara.egg-info/not-zip-safe
src/pikara.egg-info/requires.txt
src/pikara.egg-info/top_level.txt
tests/__init__.py
tests/test_critique.py
tests/test_opcodes.py
tests/test_parse.py